flixopt/__init__.py
flixopt/carrier.py
flixopt/clustering.py
flixopt/color_processing.py
flixopt/components.py
flixopt/config.py
flixopt/core.py
flixopt/effects.py
flixopt/elements.py
flixopt/features.py
flixopt/flow_system.py
flixopt/interface.py
flixopt/io.py
flixopt/linear_converters.py
flixopt/modeling.py
flixopt/network_app.py
flixopt/optimization.py
flixopt/optimize_accessor.py
flixopt/plot_result.py
flixopt/plotting.py
flixopt/results.py
flixopt/solvers.py
flixopt/statistics_accessor.py
flixopt/structure.py
flixopt/topology_accessor.py
flixopt/transform_accessor.py
flixopt/types.py
flixopt-5.0.4.dist-info/licenses/LICENSE
flixopt-5.0.4.dist-info/METADATA
flixopt-5.0.4.dist-info/WHEEL
flixopt-5.0.4.dist-info/top_level.txt
flixopt-5.0.4.dist-info/RECORD
