Metadata-Version: 2.4
Name: flixopt
Version: 5.0.4
Summary: Progressive flow system optimization in Python - start simple, scale to complex.
Author-email: "Chair of Building Energy Systems and Heat Supply, TU Dresden" <peter.stange@tu-dresden.de>, Felix Bumann <felixbumann387@gmail.com>, Felix Panitz <baumbude@googlemail.com>, Peter Stange <peter.stange@tu-dresden.de>
Maintainer-email: Felix Bumann <felixbumann387@gmail.com>, Peter Stange <peter.stange@tu-dresden.de>
License-Expression: MIT
Project-URL: homepage, https://tu-dresden.de/ing/maschinenwesen/iet/gewv/forschung/forschungsprojekte/flixopt
Project-URL: repository, https://github.com/flixOpt/flixopt
Project-URL: documentation, https://flixopt.github.io/flixopt/
Keywords: optimization,energy systems,numerical analysis
Classifier: Development Status :: 4 - Beta
Classifier: Programming Language :: Python :: 3.11
Classifier: Programming Language :: Python :: 3.12
Classifier: Programming Language :: Python :: 3.13
Classifier: Programming Language :: Python :: 3.14
Classifier: Intended Audience :: Developers
Classifier: Intended Audience :: Science/Research
Classifier: Topic :: Scientific/Engineering
Requires-Python: >=3.11
License-File: LICENSE
Requires-Dist: numpy<3,>=1.21.5
Requires-Dist: pandas<3,>=2.0.0
Requires-Dist: xarray<2026.0,>=2024.2.0
Requires-Dist: linopy<0.6,>=0.5.1
Requires-Dist: netcdf4<1.7.4,>=1.6.1
Requires-Dist: pyyaml<7,>=6.0.0
Requires-Dist: colorlog<7,>=6.8.0
Requires-Dist: tqdm<5,>=4.66.0
Requires-Dist: highspy<2,>=1.5.3
Requires-Dist: matplotlib<4,>=3.5.2
Requires-Dist: plotly<7,>=5.15.0
Provides-Extra: network-viz
Requires-Dist: dash<4,>=3.0.0; extra == "network-viz"
Requires-Dist: dash-cytoscape<2,>=1.0.0; extra == "network-viz"
Requires-Dist: dash-daq<1,>=0.6.0; extra == "network-viz"
Requires-Dist: networkx<4,>=3.0.0; extra == "network-viz"
Requires-Dist: werkzeug<4,>=3.0.0; extra == "network-viz"
Requires-Dist: flask<4,>=3.0.0; extra == "network-viz"
Provides-Extra: full
Requires-Dist: pyvis==0.3.2; extra == "full"
Requires-Dist: tsam<3,>=2.3.1; extra == "full"
Requires-Dist: scipy<2,>=1.15.1; extra == "full"
Requires-Dist: gurobipy<14,>=10.0.0; python_version < "3.14" and extra == "full"
Requires-Dist: dash<4,>=3.0.0; extra == "full"
Requires-Dist: dash-cytoscape<2,>=1.0.0; extra == "full"
Requires-Dist: dash-daq<1,>=0.6.0; extra == "full"
Requires-Dist: networkx<4,>=3.0.0; extra == "full"
Requires-Dist: werkzeug<4,>=3.0.0; extra == "full"
Requires-Dist: flask<4,>=3.0.0; extra == "full"
Provides-Extra: dev
Requires-Dist: pytest==8.4.2; extra == "dev"
Requires-Dist: pytest-xdist==3.8.0; extra == "dev"
Requires-Dist: nbformat==5.10.4; extra == "dev"
Requires-Dist: ruff==0.14.10; extra == "dev"
Requires-Dist: pre-commit==4.3.0; extra == "dev"
Requires-Dist: pyvis==0.3.2; extra == "dev"
Requires-Dist: tsam==2.3.9; extra == "dev"
Requires-Dist: scipy==1.16.3; extra == "dev"
Requires-Dist: gurobipy==12.0.3; python_version < "3.14" and extra == "dev"
Requires-Dist: dash==3.3.0; extra == "dev"
Requires-Dist: dash-cytoscape==1.0.2; extra == "dev"
Requires-Dist: dash-daq==0.6.0; extra == "dev"
Requires-Dist: networkx==3.0.0; extra == "dev"
Requires-Dist: werkzeug==3.1.4; extra == "dev"
Provides-Extra: docs
Requires-Dist: mkdocs==1.6.1; extra == "docs"
Requires-Dist: mkdocs-material==9.7.1; extra == "docs"
Requires-Dist: mkdocstrings-python==1.19.0; extra == "docs"
Requires-Dist: mkdocs-table-reader-plugin==3.1.0; extra == "docs"
Requires-Dist: mkdocs-gen-files==0.5.0; extra == "docs"
Requires-Dist: mkdocs-include-markdown-plugin==7.2.0; extra == "docs"
Requires-Dist: mkdocs-literate-nav==0.6.2; extra == "docs"
Requires-Dist: mkdocs-plotly-plugin==0.1.3; extra == "docs"
Requires-Dist: mkdocs-jupyter==0.25.1; extra == "docs"
Requires-Dist: markdown-include==0.8.1; extra == "docs"
Requires-Dist: pymdown-extensions==10.19.1; extra == "docs"
Requires-Dist: pygments==2.19.2; extra == "docs"
Requires-Dist: mike==2.1.3; extra == "docs"
Requires-Dist: mkdocs-git-revision-date-localized-plugin==1.5.0; extra == "docs"
Requires-Dist: mkdocs-minify-plugin==0.8.0; extra == "docs"
Requires-Dist: notebook>=7.5.0; extra == "docs"
Dynamic: license-file
